image2video/__init__.py
image2video/module.py
text2video/__init__.py
text2video/module.py
image2video-0.0.1.dist-info/METADATA
image2video-0.0.1.dist-info/WHEEL
image2video-0.0.1.dist-info/top_level.txt
image2video-0.0.1.dist-info/RECORD
